waj_bigquery/core/bigquery/manager.py
waj_bigquery/core/config.py
waj_bigquery/core/constants.py
waj_bigquery/core/models/.model-example.json
waj_bigquery/tests/__init__.py
waj_bigquery/tests/test_bq_creator.py
waj_bigquery-0.4.0.dist-info/WHEEL
waj_bigquery-0.4.0.dist-info/METADATA
waj_bigquery-0.4.0.dist-info/RECORD
