Metadata-Version: 2.1
Name: waj-bigquery
Version: 0.4.0
Summary: 
Author: Gabriel González
Author-email: gabriel@whaleandjaguar.co
Requires-Python: >=3.8,<3.10
Classifier: Programming Language :: Python :: 3
Classifier: Programming Language :: Python :: 3.8
Classifier: Programming Language :: Python :: 3.9
Requires-Dist: google-cloud-bigquery (>=3.0.1,<4.0.0)
Requires-Dist: pandas (>=1.4.4,<2.0.0)
Requires-Dist: pandas-gbq (>=0.17.6,<0.18.0)
